{"mc":{
	"monster_008_idle":{
		"frameRate":5,
		"events":[
			
			],
		"frames":[
			
			{
			"res":"D7C204EF",
			"x":456,
			"y":320
			},
			{
			"res":"E10E0F6D",
			"x":457,
			"y":321
			},
			{
			"res":"25198268",
			"x":457,
			"y":321
			},
			{
			"res":"A5FBFDBD",
			"x":458,
			"y":321
			}
			]
}},
	"res":{
		"25198268":{"x":88,"y":147,"w":85,"h":144},
		"E10E0F6D":{"x":88,"y":1,"w":85,"h":144},
		"D7C204EF":{"x":1,"y":1,"w":85,"h":145},
		"A5FBFDBD":{"x":1,"y":148,"w":85,"h":144}
	}}