{"mc":{
	"yunge_idle":{
		"frameRate":5,
		"events":[
			
			],
		"frames":[
			
			{
			"res":"27907C0B",
			"x":217,
			"y":313
			},
			{
			"res":"7E4148DB",
			"x":217,
			"y":313
			},
			{
			"res":"8DB5348B",
			"x":217,
			"y":313
			},
			{
			"res":"2197F845",
			"x":217,
			"y":313
			}
			]
}},
	"res":{
		"2197F845":{"x":1,"y":1,"w":102,"h":155},
		"27907C0B":{"x":105,"y":1,"w":102,"h":155},
		"7E4148DB":{"x":1,"y":158,"w":102,"h":155},
		"8DB5348B":{"x":105,"y":158,"w":102,"h":155}
	}}